{"Citation": {"CommonFields": {"CitationType": "research article", "Publication": "Polymer", "Title": "A novel approach to control thermal degradation of PET/organoclay nanocomposites and improve clay exfoliation", "Author": ["Ghanbari, A.", "Heuzey, M.C.", "Carreau, P.J.", "Ton-That, M.T."], "Keyword": ["Polyethylene terephthalate", "Nanocomposite", "Chain extender"], "Publisher": "Elsevier", "PublicationYear": "2013", "DOI": "10.1016/j.polymer.2012.12.066", "Volume": "54", "URL": "https://linkinghub.elsevier.com/retrieve/pii/S0032386112011287", "Language": "English", "Location": "Center for Applied Research on Polymers and Composites (CREPEC), Chemical Engineering Department, Ecole Polytechnique de Montreal, PO Box 6079, Stn Centre-Ville, Montreal, QC, Canada H3C 3A7", "DateOfCitation": "2019-05-08"}, "CitationType": {"Journal": {"ISSN": "00323861", "Issue": "4"}}}}