{"Citation": {"CommonFields": {"CitationType": "research article", "Publication": "Carbon", "Title": "Polypropylene/carbon nanotube nano/microcellular structures with high dielectric permittivity, low dielectric loss, and low percolation threshold", "Author": ["Ameli, A.", "Nofar, M.", "Park, C.B.", "P\u00f6tschke, P.", "Rizvi, G."], "Publisher": "Pergamon", "PublicationYear": "2014", "DOI": "10.1016/j.carbon.2014.01.031", "Volume": "71", "URL": "https://www.sciencedirect.com/science/article/pii/S0008622314000670?via%3Dihub", "Language": "English", "Location": "Microcellular Plastics Manufacturing Laboratory, Department of Mechanical and Industrial Engineering, University of Toronto, 5 King\u2019s College Road, Toronto M5S 3G8, Canada", "DateOfCitation": "2017-07-24"}, "CitationType": {"Journal": {"ISSN": "0008-6223"}}}}