{"Citation": {"CommonFields": {"CitationType": "research article", "Publication": "Polymer Composites", "Title": "Improvement of the mechanical properties of nano-TiO", "Author": ["Lou, Yuanhua", "Liu, Meihong", "Miao, Xiaowei", "Zhang, Li", "Wang, Xinping"], "Publisher": "Wiley Blackwell (John Wiley & Sons)", "PublicationYear": "2009", "DOI": "10.1002/pc.20905", "Volume": "31", "URL": "http://doi.wiley.com/10.1002/pc.20905", "Language": "English", "Location": "Department of Chemistry, Key Laboratory of Advanced Textile Materials and Manufacturing Technology of Education Ministry, Zhejiang Sci\u2010Tech University, XiaSha Higher Education Zone, Hangzhou 310018, China", "DateOfCitation": "2019-05-08"}, "CitationType": {"Journal": {"ISSN": "15480569", "Issue": "7"}}}}